{
  "symbol": "RAKBANK",
  "name_en": "National Bank of Ras Al Khaimah",
  "name_ar": "بنك رأس الخيمة الوطني",
  "exchange": "ADX",
  "sector": "Banks",
  "archetype": "bank",
  "currency": "AED",
  "isin": null,
  "quote": {
    "symbol": "RAKBANK",
    "price": 9.14,
    "change": 0.0,
    "change_pct": 0.0,
    "volume": 10,
    "market_cap": null,
    "high_52w": 9.581,
    "low_52w": 9.069,
    "spark": [
      9.069,
      9.093,
      9.194,
      9.282,
      9.396,
      9.308,
      9.413,
      9.314,
      9.364,
      9.344,
      9.367,
      9.386,
      9.372,
      9.475,
      9.408,
      9.377,
      9.328,
      9.449,
      9.455,
      9.38,
      9.347,
      9.396,
      9.35,
      9.337,
      9.344,
      9.421,
      9.444,
      9.476,
      9.581,
      9.14
    ],
    "prov": {
      "source_type": "official",
      "source_name": "ADX (delayed)",
      "data_quality": "delayed",
      "retrieved_at": "2026-07-02T07:31:00.093Z",
      "url": null,
      "lang": null
    }
  },
  "scores": {
    "growth": {
      "pillar": "growth",
      "score": 84,
      "grade": "A",
      "subfactors": [
        {
          "key": "rev",
          "label": "Revenue growth (YoY)",
          "raw": 0.1819,
          "points": 77.3,
          "weight": 0.26,
          "note": "18.2% top-line growth",
          "contribution": 20.1
        },
        {
          "key": "profit",
          "label": "Earnings growth (YoY)",
          "raw": 0.2684,
          "points": 92.10000000000001,
          "weight": 0.24,
          "note": "26.8% earnings growth",
          "contribution": 22.1
        },
        {
          "key": "cagr",
          "label": "Revenue CAGR (3y)",
          "raw": 0.1626,
          "points": 81.3,
          "weight": 0.16,
          "note": "16.3% 3-year CAGR",
          "contribution": 13.0
        },
        {
          "key": "margin",
          "label": "Margin direction",
          "raw": 0.0205,
          "points": 72.14285714285714,
          "weight": 0.14,
          "note": "expanding margins",
          "contribution": 10.1
        },
        {
          "key": "reinvest",
          "label": "Reinvestment / capex productivity",
          "raw": 0.81,
          "points": 87.14285714285717,
          "weight": 0.1,
          "note": "capital being put to work",
          "contribution": 8.7
        },
        {
          "key": "catalysts",
          "label": "Forward catalysts",
          "raw": 4,
          "points": 100.0,
          "weight": 0.1,
          "note": "4 identified growth catalyst(s)",
          "contribution": 10.0
        }
      ]
    },
    "stability": {
      "pillar": "stability",
      "score": 60,
      "grade": "C+",
      "subfactors": [
        {
          "key": "lev",
          "label": "Leverage (net debt / EBITDA)",
          "raw": 0.82,
          "points": 92.88888888888889,
          "weight": 0.08,
          "note": "conservative balance sheet",
          "contribution": 7.4
        },
        {
          "key": "liq",
          "label": "Liquidity (current ratio)",
          "raw": 1.63,
          "points": 59.28571428571426,
          "weight": 0.14,
          "note": "comfortable liquidity",
          "contribution": 8.3
        },
        {
          "key": "ocf",
          "label": "Operating cash-flow consistency",
          "raw": 0.85,
          "points": 78.57142857142858,
          "weight": 0.24,
          "note": "steady cash generation",
          "contribution": 18.9
        },
        {
          "key": "vol",
          "label": "Price volatility (annualised)",
          "raw": 0.331,
          "points": 50.93023255813954,
          "weight": 0.14,
          "note": "volatile",
          "contribution": 7.1
        },
        {
          "key": "gov",
          "label": "Governance cadence",
          "raw": 0.51,
          "points": 30.000000000000004,
          "weight": 0.18,
          "note": "irregular cadence",
          "contribution": 5.4
        },
        {
          "key": "disc",
          "label": "Disclosure quality",
          "raw": 0.9,
          "points": 85.71428571428574,
          "weight": 0.1,
          "note": "timely + complete",
          "contribution": 8.6
        },
        {
          "key": "macro",
          "label": "Macro / commodity sensitivity",
          "raw": 0.57,
          "points": 41.25000000000001,
          "weight": 0.16,
          "note": "macro-exposed",
          "contribution": 6.6
        }
      ]
    },
    "dividend": {
      "pillar": "dividend",
      "score": 68,
      "grade": "B",
      "subfactors": [
        {
          "key": "yield",
          "label": "Yield (quality-adjusted)",
          "raw": 0.0437,
          "points": 72.83333333333334,
          "weight": 0.18,
          "note": "4.37% yield",
          "contribution": 13.1
        },
        {
          "key": "payout",
          "label": "Payout ratio",
          "raw": 0.43,
          "points": 84.69999999999999,
          "weight": 0.2,
          "note": "43% of earnings paid out",
          "contribution": 16.9
        },
        {
          "key": "fcf",
          "label": "Free-cash-flow coverage",
          "raw": 1.11,
          "points": 36.42857142857144,
          "weight": 0.22,
          "note": "thin / uncovered coverage",
          "contribution": 8.0
        },
        {
          "key": "debt",
          "label": "Debt pressure on payout",
          "raw": 0.43,
          "points": 58.75000000000001,
          "weight": 0.14,
          "note": "debt may pressure payout",
          "contribution": 8.2
        },
        {
          "key": "cuts",
          "label": "Cut / miss history",
          "raw": 0,
          "points": 100.0,
          "weight": 0.16,
          "note": "clean payment record",
          "contribution": 16.0
        },
        {
          "key": "freq",
          "label": "Frequency & regularity",
          "raw": "annual",
          "points": 55.0,
          "weight": 0.1,
          "note": "annual distribution, 3y streak",
          "contribution": 5.5
        }
      ]
    },
    "headline": 72,
    "headline_grade": "B+",
    "archetype": "bank",
    "engine": "deterministic-v1"
  },
  "fundamentals": {
    "revenue_growth": 0.1819,
    "profit_growth": 0.2684,
    "revenue_cagr_3y": 0.1626,
    "margin_trend": 0.0205,
    "reinvestment": 0.81,
    "catalysts": 4,
    "net_debt_to_ebitda": 0.82,
    "current_ratio": 1.63,
    "ocf_consistency": 0.85,
    "price_volatility": 0.331,
    "governance_cadence": 0.51,
    "disclosure_quality": 0.9,
    "macro_sensitivity": 0.57,
    "dividend_yield": 0.0437,
    "payout_ratio": 0.43,
    "fcf_coverage": 1.11,
    "net_debt_pressure": 0.43,
    "cut_history": 0,
    "frequency": "annual",
    "years_paid": 3
  },
  "overview": {
    "business_summary_en": "National Bank of Ras Al Khaimah is a UAE bank offering corporate, retail and Islamic financial services, listed on ADX in the Banks sector.",
    "business_summary_ar": "بنك رأس الخيمة الوطني شركة مدرجة في سوق أبوظبي ضمن قطاع Banks.",
    "index_membership": [
      "ADX"
    ],
    "quick_stats": {
      "market_cap": null,
      "volume": 10,
      "high_52w": 9.581,
      "low_52w": 9.069,
      "dividend_yield": 0.0437
    },
    "top_catalysts": [
      "Solid growth profile (Growth 84/100)",
      "Dependable dividend characteristics (Dividend 68/100)"
    ],
    "top_risks": [
      "Execution and macro conditions remain the key swing factors"
    ]
  },
  "disclosures": [
    {
      "id": "RAKBANK-8-1782887460",
      "symbol": "RAKBANK",
      "event_type": "agm_invitation",
      "title_src": "دعوة للجمعية العمومية",
      "title_en": "Invitation to the General Assembly Meeting",
      "title_lang": "ar",
      "published_at": "2026-07-01T06:31:00+00:00",
      "body_excerpt": "AGM agenda includes dividend approval, board election and auditor appointment.",
      "url": null,
      "summary_en": "Invitation to the General Assembly Meeting. AGM agenda includes dividend approval, board election and auditor appointment.",
      "summary_ar": "دعوة للجمعية العمومية",
      "why_it_matters": "The AGM is where dividends and board changes are formally approved.",
      "materiality": 16,
      "sentiment": "positive",
      "linked_entities": [],
      "prov": {
        "source_type": "mock",
        "source_name": "Demo seed",
        "data_quality": "demo",
        "retrieved_at": "2026-07-02T07:31:00+00:00",
        "url": null,
        "lang": null
      },
      "translation_app_generated": true
    },
    {
      "id": "RAKBANK-3-1782171060",
      "symbol": "RAKBANK",
      "event_type": "dividend",
      "title_src": "الإعلان عن توزيع أرباح نقدية",
      "title_en": "Cash dividend distribution announcement",
      "title_lang": "ar",
      "published_at": "2026-06-22T23:31:00+00:00",
      "body_excerpt": "Company announces a cash dividend per share with entitlement and payment dates.",
      "url": null,
      "summary_en": "Cash dividend distribution announcement. Company announces a cash dividend per share with entitlement and payment dates.",
      "summary_ar": "الإعلان عن توزيع أرباح نقدية",
      "why_it_matters": "Dividend actions are a primary driver of total return for UAE income investors.",
      "materiality": 85,
      "sentiment": "neutral",
      "linked_entities": [],
      "prov": {
        "source_type": "mock",
        "source_name": "Demo seed",
        "data_quality": "demo",
        "retrieved_at": "2026-07-02T07:31:00+00:00",
        "url": null,
        "lang": null
      },
      "translation_app_generated": true
    },
    {
      "id": "RAKBANK-2-1782113460",
      "symbol": "RAKBANK",
      "event_type": "capital_raise",
      "title_src": "Capital increase / sukuk issuance",
      "title_en": "Capital increase / sukuk issuance",
      "title_lang": "en",
      "published_at": "2026-06-22T07:31:00+00:00",
      "body_excerpt": "Board approved a capital markets transaction to fund expansion.",
      "url": null,
      "summary_en": "Capital increase / sukuk issuance. Board approved a capital markets transaction to fund expansion.",
      "summary_ar": "",
      "why_it_matters": "New capital changes the balance sheet, dilution and funding outlook.",
      "materiality": 72,
      "sentiment": "positive",
      "linked_entities": [],
      "prov": {
        "source_type": "mock",
        "source_name": "Demo seed",
        "data_quality": "demo",
        "retrieved_at": "2026-07-02T07:31:00+00:00",
        "url": null,
        "lang": null
      },
      "translation_app_generated": false
    },
    {
      "id": "RAKBANK-1-1782081060",
      "symbol": "RAKBANK",
      "event_type": "agm_invitation",
      "title_src": "دعوة للجمعية العمومية",
      "title_en": "Invitation to the General Assembly Meeting",
      "title_lang": "ar",
      "published_at": "2026-06-21T22:31:00+00:00",
      "body_excerpt": "AGM agenda includes dividend approval, board election and auditor appointment.",
      "url": null,
      "summary_en": "Invitation to the General Assembly Meeting. AGM agenda includes dividend approval, board election and auditor appointment.",
      "summary_ar": "دعوة للجمعية العمومية",
      "why_it_matters": "The AGM is where dividends and board changes are formally approved.",
      "materiality": 51,
      "sentiment": "neutral",
      "linked_entities": [],
      "prov": {
        "source_type": "mock",
        "source_name": "Demo seed",
        "data_quality": "demo",
        "retrieved_at": "2026-07-02T07:31:00+00:00",
        "url": null,
        "lang": null
      },
      "translation_app_generated": true
    },
    {
      "id": "RAKBANK-4-1781667060",
      "symbol": "RAKBANK",
      "event_type": "agm_invitation",
      "title_src": "دعوة للجمعية العمومية",
      "title_en": "Invitation to the General Assembly Meeting",
      "title_lang": "ar",
      "published_at": "2026-06-17T03:31:00+00:00",
      "body_excerpt": "AGM agenda includes dividend approval, board election and auditor appointment.",
      "url": null,
      "summary_en": "Invitation to the General Assembly Meeting. AGM agenda includes dividend approval, board election and auditor appointment.",
      "summary_ar": "دعوة للجمعية العمومية",
      "why_it_matters": "The AGM is where dividends and board changes are formally approved.",
      "materiality": 65,
      "sentiment": "neutral",
      "linked_entities": [],
      "prov": {
        "source_type": "mock",
        "source_name": "Demo seed",
        "data_quality": "demo",
        "retrieved_at": "2026-07-02T07:31:00+00:00",
        "url": null,
        "lang": null
      },
      "translation_app_generated": true
    },
    {
      "id": "RAKBANK-6-1780007460",
      "symbol": "RAKBANK",
      "event_type": "dividend",
      "title_src": "الإعلان عن توزيع أرباح نقدية",
      "title_en": "Cash dividend distribution announcement",
      "title_lang": "ar",
      "published_at": "2026-05-28T22:31:00+00:00",
      "body_excerpt": "Company announces a cash dividend per share with entitlement and payment dates.",
      "url": null,
      "summary_en": "Cash dividend distribution announcement. Company announces a cash dividend per share with entitlement and payment dates.",
      "summary_ar": "الإعلان عن توزيع أرباح نقدية",
      "why_it_matters": "Dividend actions are a primary driver of total return for UAE income investors.",
      "materiality": 39,
      "sentiment": "neutral",
      "linked_entities": [],
      "prov": {
        "source_type": "mock",
        "source_name": "Demo seed",
        "data_quality": "demo",
        "retrieved_at": "2026-07-02T07:31:00+00:00",
        "url": null,
        "lang": null
      },
      "translation_app_generated": true
    },
    {
      "id": "RAKBANK-0-1779089460",
      "symbol": "RAKBANK",
      "event_type": "results",
      "title_src": "نتائج مالية للفترة",
      "title_en": "Financial results for the period",
      "title_lang": "ar",
      "published_at": "2026-05-18T07:31:00+00:00",
      "body_excerpt": "Board approved the interim financial statements; revenue and net profit disclosed.",
      "url": null,
      "summary_en": "Financial results for the period. Board approved the interim financial statements; revenue and net profit disclosed.",
      "summary_ar": "نتائج مالية للفترة",
      "why_it_matters": "Earnings set the near-term tone and feed directly into the dividend and growth picture.",
      "materiality": 78,
      "sentiment": "neutral",
      "linked_entities": [],
      "prov": {
        "source_type": "mock",
        "source_name": "Demo seed",
        "data_quality": "demo",
        "retrieved_at": "2026-07-02T07:31:00+00:00",
        "url": null,
        "lang": null
      },
      "translation_app_generated": true
    },
    {
      "id": "RAKBANK-7-1776663060",
      "symbol": "RAKBANK",
      "event_type": "dividend",
      "title_src": "الإعلان عن توزيع أرباح نقدية",
      "title_en": "Cash dividend distribution announcement",
      "title_lang": "ar",
      "published_at": "2026-04-20T05:31:00+00:00",
      "body_excerpt": "Company announces a cash dividend per share with entitlement and payment dates.",
      "url": null,
      "summary_en": "Cash dividend distribution announcement. Company announces a cash dividend per share with entitlement and payment dates.",
      "summary_ar": "الإعلان عن توزيع أرباح نقدية",
      "why_it_matters": "Dividend actions are a primary driver of total return for UAE income investors.",
      "materiality": 33,
      "sentiment": "neutral",
      "linked_entities": [],
      "prov": {
        "source_type": "mock",
        "source_name": "Demo seed",
        "data_quality": "demo",
        "retrieved_at": "2026-07-02T07:31:00+00:00",
        "url": null,
        "lang": null
      },
      "translation_app_generated": true
    },
    {
      "id": "RAKBANK-5-1775878260",
      "symbol": "RAKBANK",
      "event_type": "acquisition",
      "title_src": "Acquisition / strategic transaction",
      "title_en": "Acquisition / strategic transaction",
      "title_lang": "en",
      "published_at": "2026-04-11T03:31:00+00:00",
      "body_excerpt": "Company entered an agreement to acquire a strategic asset, subject to approvals.",
      "url": null,
      "summary_en": "Acquisition / strategic transaction. Company entered an agreement to acquire a strategic asset, subject to approvals.",
      "summary_ar": "",
      "why_it_matters": "M&A can re-rate the growth and risk profile materially.",
      "materiality": 80,
      "sentiment": "neutral",
      "linked_entities": [],
      "prov": {
        "source_type": "mock",
        "source_name": "Demo seed",
        "data_quality": "demo",
        "retrieved_at": "2026-07-02T07:31:00+00:00",
        "url": null,
        "lang": null
      },
      "translation_app_generated": false
    }
  ],
  "meetings": [
    {
      "symbol": "RAKBANK",
      "kind": "board",
      "date": "2026-07-31",
      "status": "upcoming",
      "agenda": [
        "Review interim results",
        "Consider cash dividend"
      ],
      "topics": [
        "dividend"
      ],
      "resolutions": [],
      "outcome_summary": "",
      "prov": {
        "source_type": "mock",
        "source_name": "Demo seed",
        "data_quality": "demo",
        "retrieved_at": "2026-07-02T07:31:00+00:00",
        "url": null,
        "lang": null
      }
    },
    {
      "symbol": "RAKBANK",
      "kind": "agm",
      "date": "2026-08-16",
      "status": "upcoming",
      "agenda": [
        "Approve dividend",
        "Elect board",
        "Appoint auditor"
      ],
      "topics": [
        "dividend",
        "board_election"
      ],
      "resolutions": [],
      "outcome_summary": "",
      "prov": {
        "source_type": "mock",
        "source_name": "Demo seed",
        "data_quality": "demo",
        "retrieved_at": "2026-07-02T07:31:00+00:00",
        "url": null,
        "lang": null
      }
    },
    {
      "symbol": "RAKBANK",
      "kind": "board",
      "date": "2026-04-07",
      "status": "held",
      "agenda": [
        "Approve annual results"
      ],
      "topics": [
        "dividend",
        "buyback"
      ],
      "resolutions": [
        "Approved annual results",
        "Recommended cash dividend"
      ],
      "outcome_summary": "Annual results approved; dividend recommended to AGM.",
      "prov": {
        "source_type": "mock",
        "source_name": "Demo seed",
        "data_quality": "demo",
        "retrieved_at": "2026-07-02T07:31:00+00:00",
        "url": null,
        "lang": null
      }
    }
  ],
  "dividends": [
    {
      "symbol": "RAKBANK",
      "amount": 0.5546,
      "currency": "AED",
      "agm_date": "2026-07-14",
      "entitlement_date": "2026-08-03",
      "ex_date": "2026-08-02",
      "payment_date": "2026-08-23",
      "frequency": "annual",
      "fiscal_year": "2026",
      "prov": {
        "source_type": "mock",
        "source_name": "Demo seed",
        "data_quality": "demo",
        "retrieved_at": "2026-07-02T07:31:00+00:00",
        "url": null,
        "lang": null
      }
    },
    {
      "symbol": "RAKBANK",
      "amount": 0.5546,
      "currency": "AED",
      "agm_date": "2026-05-29",
      "entitlement_date": "2026-06-16",
      "ex_date": "2026-06-15",
      "payment_date": "2026-07-02",
      "frequency": "annual",
      "fiscal_year": "2026",
      "prov": {
        "source_type": "mock",
        "source_name": "Demo seed",
        "data_quality": "demo",
        "retrieved_at": "2026-07-02T07:31:00+00:00",
        "url": null,
        "lang": null
      }
    },
    {
      "symbol": "RAKBANK",
      "amount": 0.5546,
      "currency": "AED",
      "agm_date": "2025-05-25",
      "entitlement_date": "2025-06-12",
      "ex_date": "2025-06-11",
      "payment_date": "2025-06-28",
      "frequency": "annual",
      "fiscal_year": "2025",
      "prov": {
        "source_type": "mock",
        "source_name": "Demo seed",
        "data_quality": "demo",
        "retrieved_at": "2026-07-02T07:31:00+00:00",
        "url": null,
        "lang": null
      }
    }
  ],
  "ownership": {
    "symbol": "RAKBANK",
    "top_holders": [
      {
        "name": "Government / sovereign entity",
        "pct": 53.3
      },
      {
        "name": "Strategic shareholder",
        "pct": 16.8
      },
      {
        "name": "Free float",
        "pct": 29.9
      }
    ],
    "foreign_permitted": 49,
    "foreign_actual": 10.5,
    "foreign_available": 38.5,
    "free_float": 29.9,
    "prov": {
      "source_type": "mock",
      "source_name": "Demo seed",
      "data_quality": "demo",
      "retrieved_at": "2026-07-02T07:31:00+00:00",
      "url": null,
      "lang": null
    }
  },
  "financials": {
    "years": [
      2022,
      2023,
      2024,
      2025,
      2026
    ],
    "revenue": [
      1793700000.0,
      2120000000.0,
      2505600000.0,
      2961300000.0,
      3500000000.0
    ],
    "net_income": [
      323800000.0,
      404400000.0,
      503600000.0,
      625600000.0,
      775300000.0
    ],
    "operating_cash_flow": [
      373900000.0,
      467100000.0,
      581700000.0,
      722500000.0,
      895400000.0
    ],
    "ratios": {
      "net_margin": 0.2215,
      "net_debt_to_ebitda": 0.82,
      "current_ratio": 1.63,
      "payout_ratio": 0.43
    },
    "revenue_cagr_3y": 0.1626,
    "data_quality": "demo"
  },
  "global_factors": {
    "exposures": [
      {
        "key": "rates",
        "label_en": "US / UAE interest rates",
        "label_ar": "أسعار الفائدة",
        "unit": "%",
        "wb_series": null,
        "latest_value": null,
        "latest_change_pct": null
      },
      {
        "key": "uae_credit",
        "label_en": "UAE credit demand",
        "label_ar": "الطلب على الائتمان",
        "unit": "idx",
        "wb_series": null,
        "latest_value": null,
        "latest_change_pct": null
      },
      {
        "key": "oil",
        "label_en": "Crude oil (Brent)",
        "label_ar": "النفط الخام",
        "unit": "USD/bbl",
        "wb_series": "CRUDE_BRENT",
        "latest_value": 77.2,
        "latest_change_pct": -0.0103
      }
    ],
    "commodities": [
      {
        "series": "CRUDE_BRENT",
        "label": "Brent crude",
        "value": 77.2,
        "change_pct": -0.0103,
        "unit": "USD/bbl",
        "as_of": "2026-07-02T07:31:00+00:00",
        "prov": {
          "source_type": "mock",
          "source_name": "Demo seed",
          "data_quality": "demo",
          "retrieved_at": "2026-07-02T07:31:00+00:00",
          "url": null,
          "lang": null
        }
      },
      {
        "series": "NGAS_EUR",
        "label": "Natural gas (EU)",
        "value": 11.22,
        "change_pct": -0.024,
        "unit": "USD/mmbtu",
        "as_of": "2026-07-02T07:31:00+00:00",
        "prov": {
          "source_type": "mock",
          "source_name": "Demo seed",
          "data_quality": "demo",
          "retrieved_at": "2026-07-02T07:31:00+00:00",
          "url": null,
          "lang": null
        }
      },
      {
        "series": "ALUMINUM",
        "label": "Aluminium",
        "value": 2396.1,
        "change_pct": -0.022,
        "unit": "USD/mt",
        "as_of": "2026-07-02T07:31:00+00:00",
        "prov": {
          "source_type": "mock",
          "source_name": "Demo seed",
          "data_quality": "demo",
          "retrieved_at": "2026-07-02T07:31:00+00:00",
          "url": null,
          "lang": null
        }
      },
      {
        "series": "UREA_EE_BULK",
        "label": "Urea",
        "value": 352.08,
        "change_pct": -0.022,
        "unit": "USD/mt",
        "as_of": "2026-07-02T07:31:00+00:00",
        "prov": {
          "source_type": "mock",
          "source_name": "Demo seed",
          "data_quality": "demo",
          "retrieved_at": "2026-07-02T07:31:00+00:00",
          "url": null,
          "lang": null
        }
      },
      {
        "series": "WHEAT_US_HRW",
        "label": "Wheat",
        "value": 242.82,
        "change_pct": -0.0089,
        "unit": "USD/mt",
        "as_of": "2026-07-02T07:31:00+00:00",
        "prov": {
          "source_type": "mock",
          "source_name": "Demo seed",
          "data_quality": "demo",
          "retrieved_at": "2026-07-02T07:31:00+00:00",
          "url": null,
          "lang": null
        }
      },
      {
        "series": "GOLD",
        "label": "Gold",
        "value": 2470.68,
        "change_pct": 0.0381,
        "unit": "USD/oz",
        "as_of": "2026-07-02T07:31:00+00:00",
        "prov": {
          "source_type": "mock",
          "source_name": "Demo seed",
          "data_quality": "demo",
          "retrieved_at": "2026-07-02T07:31:00+00:00",
          "url": null,
          "lang": null
        }
      }
    ],
    "events": [
      {
        "title": "Federal headline — global macro update 1",
        "theme": "ENERGY",
        "published_at": "2026-07-01T05:31:00+00:00",
        "domain": "bloomberg.com",
        "url": null,
        "tone": -3.75,
        "prov": {
          "source_type": "mock",
          "source_name": "GDELT (demo)",
          "data_quality": "demo",
          "retrieved_at": "2026-07-02T07:31:00+00:00",
          "url": null,
          "lang": null
        }
      },
      {
        "title": "Federal headline — global macro update 2",
        "theme": "AGRICULTURE",
        "published_at": "2026-07-01T05:31:00+00:00",
        "domain": "bloomberg.com",
        "url": null,
        "tone": -4.32,
        "prov": {
          "source_type": "mock",
          "source_name": "GDELT (demo)",
          "data_quality": "demo",
          "retrieved_at": "2026-07-02T07:31:00+00:00",
          "url": null,
          "lang": null
        }
      },
      {
        "title": "Federal headline — global macro update 3",
        "theme": "TRADE",
        "published_at": "2026-06-29T13:31:00+00:00",
        "domain": "thenationalnews.com",
        "url": null,
        "tone": 1.18,
        "prov": {
          "source_type": "mock",
          "source_name": "GDELT (demo)",
          "data_quality": "demo",
          "retrieved_at": "2026-07-02T07:31:00+00:00",
          "url": null,
          "lang": null
        }
      }
    ],
    "note": "Exposure map links this name to global drivers; commodity values from World Bank, events from GDELT (or demo)."
  },
  "ai_analysis": {
    "short_term": {
      "stance": "Neutral",
      "confidence": "high",
      "reasons": [
        "A high-materiality disclosure (85/100) is in the recent flow",
        "Recent disclosure tone skews positive"
      ],
      "risks": [
        "A surprise filing or a sector-wide move could shift the picture quickly"
      ],
      "what_would_change_view": "A new high-materiality disclosure, an unexpected sector move, or a sharp commodity shock in this name's exposure map."
    },
    "long_term": {
      "stance": "Bullish",
      "confidence": "medium",
      "reasons": [
        "Solid growth profile (Growth 84/100)",
        "Dependable dividend characteristics (Dividend 68/100)"
      ],
      "risks": [
        "Execution and macro conditions remain the key swing factors"
      ],
      "what_would_change_view": "A durable change in the growth, stability or dividend pillars — e.g. a re-rating in earnings, a leverage spike, or a dividend cut."
    },
    "_signal": {
      "short": {
        "stance": "Neutral",
        "confidence": "high",
        "score": 62.2,
        "reasons": [
          "A high-materiality disclosure (85/100) is in the recent flow",
          "Recent disclosure tone skews positive"
        ],
        "risks": [
          "A surprise filing or a sector-wide move could shift the picture quickly"
        ]
      },
      "long": {
        "stance": "Bullish",
        "confidence": "medium",
        "score": 71.8,
        "reasons": [
          "Solid growth profile (Growth 84/100)",
          "Dependable dividend characteristics (Dividend 68/100)"
        ],
        "risks": [
          "Execution and macro conditions remain the key swing factors"
        ]
      }
    },
    "_engine": "deterministic-signal+narration",
    "provider": "stub",
    "generated_at": "2026-07-02T07:31:00+00:00"
  },
  "generated_at": "2026-07-02T07:31:00+00:00"
}